{"v":"5.11.0","fr":29.9700012207031,"ip":0,"op":223.000009082976,"w":5245,"h":4196,"nm":"Interior UI","ddd":0,"assets":[{"id":"image_0","w":14,"h":14,"u":"images/","p":"img_0.png","e":0},{"id":"image_1","w":14,"h":14,"u":"images/","p":"img_1.png","e":0},{"id":"image_2","w":18,"h":34,"u":"images/","p":"img_2.png","e":0},{"id":"image_3","w":18,"h":34,"u":"images/","p":"img_3.png","e":0},{"id":"image_4","w":18,"h":34,"u":"images/","p":"img_4.png","e":0},{"id":"image_5","w":360,"h":319,"u":"images/","p":"img_5.png","e":0},{"id":"image_6","w":130,"h":220,"u":"images/","p":"img_6.png","e":0},{"id":"image_7","w":96,"h":16,"u":"images/","p":"img_7.png","e":0},{"id":"image_8","w":276,"h":89,"u":"images/","p":"img_8.png","e":0},{"id":"image_9","w":26,"h":26,"u":"images/","p":"img_9.png","e":0},{"id":"image_10","w":15,"h":29,"u":"images/","p":"img_10.png","e":0},{"id":"image_11","w":26,"h":26,"u":"images/","p":"img_11.png","e":0},{"id":"image_12","w":216,"h":220,"u":"images/","p":"img_12.png","e":0},{"id":"image_13","w":5246,"h":4197,"u":"images/","p":"img_13.png","e":0},{"id":"comp_0","nm":"chair","fr":29.9700012207031,"layers":[{"ddd":0,"ind":1,"ty":2,"nm":"Layer 19","refId":"image_0","sr":1,"ks":{"o":{"a":0,"k":100,"ix":11},"r":{"a":0,"k":0,"ix":10},"p":{"a":0,"k":[2911.214,2254.93,0],"ix":2,"l":2},"a":{"a":0,"k":[6.876,6.876,0],"ix":1,"l":2},"s":{"a":0,"k":[100,100,100],"ix":6,"l":2}},"ao":0,"ip":85.000003462121,"op":154.000006272549,"st":85.000003462121,"ct":1,"bm":0},{"ddd":0,"ind":2,"ty":2,"nm":"Layer 18","refId":"image_1","sr":1,"ks":{"o":{"a":0,"k":100,"ix":11},"r":{"a":0,"k":0,"ix":10},"p":{"a":0,"k":[2640.901,2254.93,0],"ix":2,"l":2},"a":{"a":0,"k":[6.876,6.876,0],"ix":1,"l":2},"s":{"a":0,"k":[100,100,100],"ix":6,"l":2}},"ao":0,"ip":85.000003462121,"op":154.000006272549,"st":85.000003462121,"ct":1,"bm":0},{"ddd":0,"ind":3,"ty":2,"nm":"Layer 17","refId":"image_2","sr":1,"ks":{"o":{"a":0,"k":100,"ix":11},"r":{"a":0,"k":0,"ix":10},"p":{"a":0,"k":[2826.81,2184.686,0],"ix":2,"l":2},"a":{"a":0,"k":[8.535,16.821,0],"ix":1,"l":2},"s":{"a":0,"k":[100,100,100],"ix":6,"l":2}},"ao":0,"ip":85.000003462121,"op":154.000006272549,"st":85.000003462121,"ct":1,"bm":0},{"ddd":0,"ind":4,"ty":2,"nm":"Layer 16","refId":"image_3","sr":1,"ks":{"o":{"a":0,"k":100,"ix":11},"r":{"a":0,"k":0,"ix":10},"p":{"a":0,"k":[2778.367,2184.686,0],"ix":2,"l":2},"a":{"a":0,"k":[8.535,16.821,0],"ix":1,"l":2},"s":{"a":0,"k":[100,100,100],"ix":6,"l":2}},"ao":0,"ip":85.000003462121,"op":154.000006272549,"st":85.000003462121,"ct":1,"bm":0},{"ddd":0,"ind":5,"ty":2,"nm":"Layer 15","refId":"image_4","sr":1,"ks":{"o":{"a":0,"k":100,"ix":11},"r":{"a":0,"k":0,"ix":10},"p":{"a":0,"k":[2729.925,2184.686,0],"ix":2,"l":2},"a":{"a":0,"k":[8.535,16.821,0],"ix":1,"l":2},"s":{"a":0,"k":[100,100,100],"ix":6,"l":2}},"ao":0,"ip":85.000003462121,"op":154.000006272549,"st":85.000003462121,"ct":1,"bm":0},{"ddd":0,"ind":6,"ty":4,"nm":"Layer 14 Outlines","sr":1,"ks":{"o":{"a":0,"k":100,"ix":11},"r":{"a":0,"k":0,"ix":10},"p":{"a":0,"k":[2776.057,2287.454,0],"ix":2,"l":2},"a":{"a":0,"k":[91.093,34.017,0],"ix":1,"l":2},"s":{"a":0,"k":[100,100,100],"ix":6,"l":2}},"ao":0,"shapes":[{"ty":"gr","it":[{"ind":0,"ty":"sh","ix":1,"ks":{"a":1,"k":[{"i":{"x":0.833,"y":0.833},"o":{"x":0.167,"y":0.167},"t":85,"s":[{"i":[[-5.271,-2.441],[0,0],[0,0],[0,0],[15.535,0],[0,0],[0,0],[2.687,-12.744],[0,0],[-6.183,0],[0,0],[0,0]],"o":[[0,0],[0,0],[0,0],[0,-15.534],[0,0],[0,0],[-13.54,0],[0,0],[5.272,-2.441],[0,0],[0,0],[6.183,0]],"v":[[90.844,-29.962],[90.844,33.767],[90.144,33.767],[90.144,22.135],[61.975,-6.034],[15.089,-6.034],[-63.283,-6.034],[-90.844,16.308],[-90.844,-29.962],[-73.522,-33.767],[-12.037,-33.767],[73.521,-33.767]],"c":true}]},{"i":{"x":0.833,"y":0.833},"o":{"x":0.167,"y":0.167},"t":99,"s":[{"i":[[-5.271,-2.441],[0,0],[0,0],[0,0],[15.535,0],[30,-0.58],[0,0],[2.687,-12.744],[0,0],[-6.183,0],[0,0],[0,0]],"o":[[0,0],[0,0],[0,0],[0,-15.534],[0,0],[-30,0.58],[-13.54,0],[0,0],[5.272,-2.441],[0,0],[0,0],[6.183,0]],"v":[[90.844,-29.962],[90.844,33.767],[90.144,33.767],[90.144,22.135],[61.975,-6.034],[-2.057,9.966],[-63.283,-6.034],[-90.844,16.308],[-90.844,-29.962],[-73.522,-33.767],[-2.057,-13.767],[73.521,-33.767]],"c":true}]},{"i":{"x":0.833,"y":0.833},"o":{"x":0.167,"y":0.167},"t":113,"s":[{"i":[[-5.271,-2.441],[0,0],[0,0],[0,0],[15.535,0],[30,-0.58],[0,0],[2.687,-12.744],[0,0],[-6.183,0],[0,0],[0,0]],"o":[[0,0],[0,0],[0,0],[0,-15.534],[0,0],[-30,0.58],[-13.54,0],[0,0],[5.272,-2.441],[0,0],[0,0],[6.183,0]],"v":[[90.844,-29.962],[90.844,33.767],[90.144,33.767],[90.144,22.135],[61.975,-6.034],[-4.057,-8.034],[-63.283,-6.034],[-90.844,16.308],[-90.844,-29.962],[-73.522,-33.767],[-2.057,-31.767],[73.521,-33.767]],"c":true}]},{"i":{"x":0.833,"y":0.833},"o":{"x":0.167,"y":0.167},"t":126,"s":[{"i":[[-5.271,-2.441],[0,0],[0,0],[0,0],[15.535,0],[0,0],[0,0],[2.687,-12.744],[0,0],[-6.183,0],[0,0],[0,0]],"o":[[0,0],[0,0],[0,0],[0,-15.534],[0,0],[0,0],[-13.54,0],[0,0],[5.272,-2.441],[0,0],[0,0],[6.183,0]],"v":[[90.844,-29.962],[90.844,33.767],[90.144,33.767],[90.144,22.135],[61.975,-6.034],[15.089,-6.034],[-63.283,-6.034],[-90.844,16.308],[-90.844,-29.962],[-73.522,-33.767],[-12.037,-33.767],[73.521,-33.767]],"c":true}]},{"i":{"x":0.833,"y":0.833},"o":{"x":0.167,"y":0.167},"t":140,"s":[{"i":[[-5.271,-2.441],[0,0],[0,0],[0,0],[15.535,0],[30,-0.58],[0,0],[2.687,-12.744],[0,0],[-6.183,0],[0,0],[0,0]],"o":[[0,0],[0,0],[0,0],[0,-15.534],[0,0],[-30,0.58],[-13.54,0],[0,0],[5.272,-2.441],[0,0],[0,0],[6.183,0]],"v":[[90.844,-29.962],[90.844,33.767],[90.144,33.767],[90.144,22.135],[61.975,-6.034],[-2.057,9.966],[-63.283,-6.034],[-90.844,16.308],[-90.844,-29.962],[-73.522,-33.767],[-2.057,-13.767],[73.521,-33.767]],"c":true}]},{"t":154.000006272549,"s":[{"i":[[-5.271,-2.441],[0,0],[0,0],[0,0],[15.535,0],[30,-0.58],[0,0],[2.687,-12.744],[0,0],[-6.183,0],[0,0],[0,0]],"o":[[0,0],[0,0],[0,0],[0,-15.534],[0,0],[-30,0.58],[-13.54,0],[0,0],[5.272,-2.441],[0,0],[0,0],[6.183,0]],"v":[[90.844,-29.962],[90.844,33.767],[90.144,33.767],[90.144,22.135],[61.975,-6.034],[-4.057,-8.034],[-63.283,-6.034],[-90.844,16.308],[-90.844,-29.962],[-73.522,-33.767],[-2.057,-31.767],[73.521,-33.767]],"c":true}]}],"ix":2},"nm":"Path 1","mn":"ADBE Vector Shape - Group","hd":false},{"ty":"fl","c":{"a":0,"k":[0.984313785329,0.690196078431,0.231372563979,1],"ix":4},"o":{"a":0,"k":100,"ix":5},"r":1,"bm":0,"nm":"Fill 1","mn":"ADBE Vector Graphic - Fill","hd":false},{"ty":"tr","p":{"a":0,"k":[91.094,34.017],"ix":2},"a":{"a":0,"k":[0,0],"ix":1},"s":{"a":0,"k":[100,100],"ix":3},"r":{"a":0,"k":0,"ix":6},"o":{"a":0,"k":100,"ix":7},"sk":{"a":0,"k":0,"ix":4},"sa":{"a":0,"k":0,"ix":5},"nm":"Transform"}],"nm":"Group 1","np":2,"cix":2,"bm":0,"ix":1,"mn":"ADBE Vector Group","hd":false}],"ip":85.000003462121,"op":154.000006272549,"st":85.000003462121,"ct":1,"bm":0},{"ddd":0,"ind":7,"ty":2,"nm":"Layer 13","refId":"image_5","sr":1,"ks":{"o":{"a":0,"k":100,"ix":11},"r":{"a":0,"k":0,"ix":10},"p":{"a":0,"k":[2776.057,2254.684,0],"ix":2,"l":2},"a":{"a":0,"k":[179.72,159.172,0],"ix":1,"l":2},"s":{"a":0,"k":[100,100,100],"ix":6,"l":2}},"ao":0,"ip":85.000003462121,"op":154.000006272549,"st":85.000003462121,"ct":1,"bm":0}]},{"id":"comp_1","nm":"flower","fr":29.9700012207031,"layers":[{"ddd":0,"ind":1,"ty":4,"nm":"Layer 12 Outlines","sr":1,"ks":{"o":{"a":0,"k":100,"ix":11},"r":{"a":0,"k":0,"ix":10},"p":{"a":0,"k":[2371.883,2134.125,0],"ix":2,"l":2},"a":{"a":0,"k":[25.399,48.079,0],"ix":1,"l":2},"s":{"a":0,"k":[100,100,100],"ix":6,"l":2}},"ao":0,"shapes":[{"ty":"gr","it":[{"ind":0,"ty":"sh","ix":1,"ks":{"a":0,"k":{"i":[[0,-8.336],[4.697,-5.193],[0,0],[0,7.871],[-5.191,5.248]],"o":[[0,7.871],[0,0],[-4.695,-5.193],[0,-8.336],[5.192,5.248]],"v":[[8.44,2.566],[0.846,22.762],[-0.849,22.762],[-8.44,2.566],[-0.001,-18.524]],"c":true},"ix":2},"nm":"Path 1","mn":"ADBE Vector Shape - Group","hd":false},{"ind":1,"ty":"sh","ix":2,"ks":{"a":0,"k":{"i":[[3.557,7.969],[6.204,5.749],[0,0],[0,0],[3.432,-7.695],[0,-8.789],[-3.556,-7.969],[-5.74,-5.547],[0,0],[0,0],[0,0],[-3.382,7.583],[0,8.791]],"o":[[-3.434,-7.695],[0,0],[0,0],[-6.204,5.749],[-3.556,7.969],[0,8.791],[3.249,7.284],[0,0],[0,0],[0,0],[6.075,-5.695],[3.557,-7.971],[0,-8.789]],"v":[[19.787,-22.691],[5.264,-42.952],[-0.001,-47.83],[-5.267,-42.952],[-19.79,-22.691],[-25.149,2.566],[-19.79,27.825],[-6.25,47.151],[-6.25,37.946],[5.534,37.946],[5.534,47.83],[19.787,27.826],[25.149,2.566]],"c":true},"ix":2},"nm":"Path 2","mn":"ADBE Vector Shape - Group","hd":false},{"ty":"mm","mm":1,"nm":"Merge Paths 1","mn":"ADBE Vector Filter - Merge","hd":false},{"ty":"fl","c":{"a":0,"k":[0,0,0,1],"ix":4},"o":{"a":0,"k":100,"ix":5},"r":1,"bm":0,"nm":"Fill 1","mn":"ADBE Vector Graphic - Fill","hd":false},{"ty":"tr","p":{"a":0,"k":[25.399,48.08],"ix":2},"a":{"a":0,"k":[0,0],"ix":1},"s":{"a":0,"k":[100,100],"ix":3},"r":{"a":1,"k":[{"i":{"x":[0.833],"y":[0.833]},"o":{"x":[0.167],"y":[0.167]},"t":85,"s":[0]},{"i":{"x":[0.833],"y":[0.833]},"o":{"x":[0.167],"y":[0.167]},"t":95,"s":[4]},{"i":{"x":[0.833],"y":[0.833]},"o":{"x":[0.167],"y":[0.167]},"t":103,"s":[-4]},{"i":{"x":[0.833],"y":[0.833]},"o":{"x":[0.167],"y":[0.167]},"t":112,"s":[0]},{"i":{"x":[0.833],"y":[0.833]},"o":{"x":[0.167],"y":[0.167]},"t":127,"s":[0]},{"i":{"x":[0.833],"y":[0.833]},"o":{"x":[0.167],"y":[0.167]},"t":137,"s":[4]},{"i":{"x":[0.833],"y":[0.833]},"o":{"x":[0.167],"y":[0.167]},"t":145,"s":[-4]},{"t":154.000006272549,"s":[0]}],"ix":6},"o":{"a":0,"k":100,"ix":7},"sk":{"a":0,"k":0,"ix":4},"sa":{"a":0,"k":0,"ix":5},"nm":"Transform"}],"nm":"Group 1","np":4,"cix":2,"bm":0,"ix":1,"mn":"ADBE Vector Group","hd":false}],"ip":85.000003462121,"op":154.000006272549,"st":85.000003462121,"ct":1,"bm":0},{"ddd":0,"ind":2,"ty":4,"nm":"Layer 11 Outlines","sr":1,"ks":{"o":{"a":0,"k":100,"ix":11},"r":{"a":0,"k":0,"ix":10},"p":{"a":0,"k":[2321.506,2211.556,0],"ix":2,"l":2},"a":{"a":0,"k":[30.139,29.915,0],"ix":1,"l":2},"s":{"a":0,"k":[100,100,100],"ix":6,"l":2}},"ao":0,"shapes":[{"ty":"gr","it":[{"ind":0,"ty":"sh","ix":1,"ks":{"a":0,"k":{"i":[[0.237,-6.225],[4.754,4.754],[-0.237,6.227],[-4.754,-4.753]],"o":[[-6.228,0.237],[-4.753,-4.751],[6.227,-0.237],[4.751,4.754]],"v":[[12.027,12.024],[-5.256,5.25],[-12.03,-12.031],[5.254,-5.258]],"c":true},"ix":2},"nm":"Path 1","mn":"ADBE Vector Shape - Group","hd":false},{"ind":1,"ty":"sh","ix":2,"ks":{"a":0,"k":{"i":[[2.425,6.333],[5.002,5.002],[13.34,0],[0.634,-0.026],[0,0],[0,0],[-2.425,-6.333],[-5.002,-5.002],[-13.338,0],[-0.634,0.026],[0,0],[0,0]],"o":[[-2.512,-6.561],[-9.432,-9.432],[-0.634,0],[0,0],[0,0],[-0.258,6.801],[2.514,6.561],[9.432,9.432],[0.634,0],[0,0],[0,0],[0.261,-6.801]],"v":[[26.365,2.388],[15.041,-15.039],[-20.273,-29.666],[-22.185,-29.628],[-29.356,-29.355],[-29.631,-22.182],[-26.365,-2.389],[-15.04,15.038],[20.271,29.666],[22.181,29.627],[29.353,29.355],[29.627,22.184]],"c":true},"ix":2},"nm":"Path 2","mn":"ADBE Vector Shape - Group","hd":false},{"ty":"mm","mm":1,"nm":"Merge Paths 1","mn":"ADBE Vector Filter - Merge","hd":false},{"ty":"fl","c":{"a":0,"k":[0.345098039216,0.949019667682,0.866666726505,1],"ix":4},"o":{"a":0,"k":100,"ix":5},"r":1,"bm":0,"nm":"Fill 1","mn":"ADBE Vector Graphic - Fill","hd":false},{"ty":"tr","p":{"a":0,"k":[30.138,29.916],"ix":2},"a":{"a":0,"k":[0,0],"ix":1},"s":{"a":0,"k":[100,100],"ix":3},"r":{"a":1,"k":[{"i":{"x":[0.833],"y":[0.833]},"o":{"x":[0.167],"y":[0.167]},"t":85,"s":[0]},{"i":{"x":[0.833],"y":[0.833]},"o":{"x":[0.167],"y":[0.167]},"t":94,"s":[4]},{"i":{"x":[0.833],"y":[0.833]},"o":{"x":[0.167],"y":[0.167]},"t":103,"s":[-4]},{"i":{"x":[0.833],"y":[0.833]},"o":{"x":[0.167],"y":[0.167]},"t":112,"s":[0]},{"i":{"x":[0.833],"y":[0.833]},"o":{"x":[0.167],"y":[0.167]},"t":127,"s":[0]},{"i":{"x":[0.833],"y":[0.833]},"o":{"x":[0.167],"y":[0.167]},"t":136,"s":[4]},{"i":{"x":[0.833],"y":[0.833]},"o":{"x":[0.167],"y":[0.167]},"t":145,"s":[-4]},{"t":154.000006272549,"s":[0]}],"ix":6},"o":{"a":0,"k":100,"ix":7},"sk":{"a":0,"k":0,"ix":4},"sa":{"a":0,"k":0,"ix":5},"nm":"Transform"}],"nm":"Group 1","np":4,"cix":2,"bm":0,"ix":1,"mn":"ADBE Vector Group","hd":false}],"ip":85.000003462121,"op":154.000006272549,"st":85.000003462121,"ct":1,"bm":0},{"ddd":0,"ind":3,"ty":4,"nm":"Layer 10 Outlines","sr":1,"ks":{"o":{"a":0,"k":100,"ix":11},"r":{"a":0,"k":0,"ix":10},"p":{"a":0,"k":[2421.552,2211.554,0],"ix":2,"l":2},"a":{"a":0,"k":[30.139,29.915,0],"ix":1,"l":2},"s":{"a":0,"k":[100,100,100],"ix":6,"l":2}},"ao":0,"shapes":[{"ty":"gr","it":[{"ind":0,"ty":"sh","ix":1,"ks":{"a":0,"k":{"i":[[5.066,-5.066],[6.634,0.253],[-5.064,5.063],[-6.634,-0.251]],"o":[[-5.066,5.063],[-0.254,-6.634],[5.065,-5.066],[0.253,6.634]],"v":[[5.6,5.602],[-12.815,12.818],[-5.6,-5.595],[12.815,-12.816]],"c":true},"ix":2},"nm":"Path 1","mn":"ADBE Vector Shape - Group","hd":false},{"ind":1,"ty":"sh","ix":2,"ks":{"a":0,"k":{"i":[[0.261,6.8],[0,0],[0,0],[0.634,0],[9.431,-9.435],[2.515,-6.561],[-0.26,-6.803],[0,0],[0,0],[-0.636,0],[-9.429,9.432],[-2.511,6.561]],"o":[[0,0],[0,0],[-0.631,-0.023],[-13.341,0],[-5.003,5.002],[-2.424,6.334],[0,0],[0,0],[0.636,0.024],[13.338,0],[5.002,-5.002],[2.425,-6.334]],"v":[[29.627,-22.182],[29.355,-29.356],[22.181,-29.628],[20.273,-29.665],[-15.039,-15.036],[-26.365,2.388],[-29.628,22.184],[-29.355,29.355],[-22.185,29.63],[-20.267,29.665],[15.039,15.041],[26.365,-2.386]],"c":true},"ix":2},"nm":"Path 2","mn":"ADBE Vector Shape - Group","hd":false},{"ty":"mm","mm":1,"nm":"Merge Paths 1","mn":"ADBE Vector Filter - Merge","hd":false},{"ty":"fl","c":{"a":0,"k":[0.345098039216,0.949019667682,0.866666726505,1],"ix":4},"o":{"a":0,"k":100,"ix":5},"r":1,"bm":0,"nm":"Fill 1","mn":"ADBE Vector Graphic - Fill","hd":false},{"ty":"tr","p":{"a":0,"k":[30.138,29.915],"ix":2},"a":{"a":0,"k":[0,0],"ix":1},"s":{"a":0,"k":[100,100],"ix":3},"r":{"a":1,"k":[{"i":{"x":[0.833],"y":[0.833]},"o":{"x":[0.167],"y":[0.167]},"t":85,"s":[0]},{"i":{"x":[0.833],"y":[0.833]},"o":{"x":[0.167],"y":[0.167]},"t":93,"s":[4]},{"i":{"x":[0.833],"y":[0.833]},"o":{"x":[0.167],"y":[0.167]},"t":104,"s":[-4]},{"i":{"x":[0.833],"y":[0.833]},"o":{"x":[0.167],"y":[0.167]},"t":114,"s":[0]},{"i":{"x":[0.833],"y":[0.833]},"o":{"x":[0.167],"y":[0.167]},"t":125,"s":[0]},{"i":{"x":[0.833],"y":[0.833]},"o":{"x":[0.167],"y":[0.167]},"t":133,"s":[4]},{"i":{"x":[0.833],"y":[0.833]},"o":{"x":[0.167],"y":[0.167]},"t":144,"s":[-4]},{"t":154.000006272549,"s":[0]}],"ix":6},"o":{"a":0,"k":100,"ix":7},"sk":{"a":0,"k":0,"ix":4},"sa":{"a":0,"k":0,"ix":5},"nm":"Transform"}],"nm":"Group 1","np":4,"cix":2,"bm":0,"ix":1,"mn":"ADBE Vector Group","hd":false}],"ip":85.000003462121,"op":154.000006272549,"st":85.000003462121,"ct":1,"bm":0},{"ddd":0,"ind":4,"ty":2,"nm":"Layer 9","refId":"image_6","sr":1,"ks":{"o":{"a":0,"k":100,"ix":11},"r":{"a":0,"k":0,"ix":10},"p":{"a":0,"k":[2371.528,2281.637,0],"ix":2,"l":2},"a":{"a":0,"k":[64.965,109.816,0],"ix":1,"l":2},"s":{"a":0,"k":[100,100,100],"ix":6,"l":2}},"ao":0,"ip":85.000003462121,"op":154.000006272549,"st":85.000003462121,"ct":1,"bm":0}]},{"id":"comp_2","nm":"Ac","fr":29.9700012207031,"layers":[{"ddd":0,"ind":1,"ty":2,"nm":"Layer 8","refId":"image_7","sr":1,"ks":{"o":{"a":1,"k":[{"i":{"x":[0.833],"y":[0.833]},"o":{"x":[0.167],"y":[0.167]},"t":84,"s":[0]},{"i":{"x":[0.833],"y":[0.833]},"o":{"x":[0.167],"y":[0.167]},"t":106,"s":[100]},{"i":{"x":[0.833],"y":[0.833]},"o":{"x":[0.167],"y":[0.167]},"t":131,"s":[100]},{"t":154.000006272549,"s":[0]}],"ix":11},"r":{"a":0,"k":0,"ix":10},"p":{"a":0,"k":[2769.476,1803.355,0],"ix":2,"l":2},"a":{"a":0,"k":[47.506,7.52,0],"ix":1,"l":2},"s":{"a":0,"k":[100,100,100],"ix":6,"l":2}},"ao":0,"ip":84.0000034213901,"op":154.000006272549,"st":84.0000034213901,"ct":1,"bm":0},{"ddd":0,"ind":2,"ty":2,"nm":"Layer 7","refId":"image_8","sr":1,"ks":{"o":{"a":0,"k":100,"ix":11},"r":{"a":0,"k":0,"ix":10},"p":{"a":0,"k":[2770.082,1804.289,0],"ix":2,"l":2},"a":{"a":0,"k":[137.775,44.062,0],"ix":1,"l":2},"s":{"a":0,"k":[100,100,100],"ix":6,"l":2}},"ao":0,"ip":84.0000034213901,"op":154.000006272549,"st":84.0000034213901,"ct":1,"bm":0}]},{"id":"comp_3","nm":"light","fr":29.9700012207031,"layers":[{"ddd":0,"ind":1,"ty":2,"nm":"Layer 6","refId":"image_9","sr":1,"ks":{"o":{"a":1,"k":[{"i":{"x":[0.833],"y":[0.833]},"o":{"x":[0.167],"y":[0.167]},"t":86,"s":[0]},{"i":{"x":[0.833],"y":[0.833]},"o":{"x":[0.167],"y":[0.167]},"t":107,"s":[100]},{"i":{"x":[0.833],"y":[0.833]},"o":{"x":[0.167],"y":[0.167]},"t":131,"s":[100]},{"t":153.000006231818,"s":[0]}],"ix":11},"r":{"a":0,"k":0,"ix":10},"p":{"a":0,"k":[2422.648,1923.575,0],"ix":2,"l":2},"a":{"a":0,"k":[12.924,12.924,0],"ix":1,"l":2},"s":{"a":0,"k":[100,100,100],"ix":6,"l":2}},"ao":0,"ip":85.000003462121,"op":154.000006272549,"st":85.000003462121,"ct":1,"bm":0},{"ddd":0,"ind":2,"ty":2,"nm":"Layer 5","refId":"image_10","sr":1,"ks":{"o":{"a":1,"k":[{"i":{"x":[0.833],"y":[0.833]},"o":{"x":[0.167],"y":[0.167]},"t":86,"s":[0]},{"i":{"x":[0.833],"y":[0.833]},"o":{"x":[0.167],"y":[0.167]},"t":107,"s":[100]},{"i":{"x":[0.833],"y":[0.833]},"o":{"x":[0.167],"y":[0.167]},"t":131,"s":[100]},{"t":153.000006231818,"s":[0]}],"ix":11},"r":{"a":0,"k":0,"ix":10},"p":{"a":0,"k":[2380.262,1928.54,0],"ix":2,"l":2},"a":{"a":0,"k":[7.272,14.295,0],"ix":1,"l":2},"s":{"a":0,"k":[100,100,100],"ix":6,"l":2}},"ao":0,"ip":85.000003462121,"op":155.000006313279,"st":85.000003462121,"ct":1,"bm":0},{"ddd":0,"ind":3,"ty":2,"nm":"Layer 4","refId":"image_11","sr":1,"ks":{"o":{"a":1,"k":[{"i":{"x":[0.833],"y":[0.833]},"o":{"x":[0.167],"y":[0.167]},"t":86,"s":[0]},{"i":{"x":[0.833],"y":[0.833]},"o":{"x":[0.167],"y":[0.167]},"t":108,"s":[100]},{"i":{"x":[0.833],"y":[0.833]},"o":{"x":[0.167],"y":[0.167]},"t":132,"s":[100]},{"t":154.000006272549,"s":[0]}],"ix":11},"r":{"a":0,"k":0,"ix":10},"p":{"a":0,"k":[2337.176,1923.575,0],"ix":2,"l":2},"a":{"a":0,"k":[12.924,12.924,0],"ix":1,"l":2},"s":{"a":0,"k":[100,100,100],"ix":6,"l":2}},"ao":0,"ip":85.000003462121,"op":156.00000635401,"st":85.000003462121,"ct":1,"bm":0},{"ddd":0,"ind":4,"ty":4,"nm":"Layer 3 Outlines","sr":1,"ks":{"o":{"a":0,"k":100,"ix":11},"r":{"a":0,"k":0,"ix":10},"p":{"a":0,"k":[2380.262,1875.375,0],"ix":2,"l":2},"a":{"a":0,"k":[35.613,17.931,0],"ix":1,"l":2},"s":{"a":0,"k":[100,100,100],"ix":6,"l":2}},"ao":0,"shapes":[{"ty":"gr","it":[{"ind":0,"ty":"sh","ix":1,"ks":{"a":0,"k":{"i":[[0,0],[19.528,0],[0,19.531]],"o":[[0,19.531],[-19.531,0],[0,0]],"v":[[35.364,-17.681],[0.001,17.681],[-35.364,-17.681]],"c":true},"ix":2},"nm":"Path 1","mn":"ADBE Vector Shape - Group","hd":false},{"ty":"fl","c":{"a":1,"k":[{"i":{"x":[0.833],"y":[0.833]},"o":{"x":[0.167],"y":[0.167]},"t":87,"s":[0,0,0,1]},{"i":{"x":[0.833],"y":[0.833]},"o":{"x":[0.167],"y":[0.167]},"t":108,"s":[0.992156863213,0.874509811401,0.427450984716,1]},{"i":{"x":[0.833],"y":[0.833]},"o":{"x":[0.167],"y":[0.167]},"t":134,"s":[0.992156863213,0.874509811401,0.427450984716,1]},{"t":152.000006191087,"s":[0,0,0,1]}],"ix":4},"o":{"a":0,"k":100,"ix":5},"r":1,"bm":0,"nm":"Fill 1","mn":"ADBE Vector Graphic - Fill","hd":false},{"ty":"tr","p":{"a":0,"k":[35.614,17.931],"ix":2},"a":{"a":0,"k":[0,0],"ix":1},"s":{"a":0,"k":[100,100],"ix":3},"r":{"a":0,"k":0,"ix":6},"o":{"a":0,"k":100,"ix":7},"sk":{"a":0,"k":0,"ix":4},"sa":{"a":0,"k":0,"ix":5},"nm":"Transform"}],"nm":"Group 1","np":2,"cix":2,"bm":0,"ix":1,"mn":"ADBE Vector Group","hd":false}],"ip":86.0000035028518,"op":154.000006272549,"st":86.0000035028518,"ct":1,"bm":0},{"ddd":0,"ind":5,"ty":2,"nm":"Layer 2","refId":"image_12","sr":1,"ks":{"o":{"a":0,"k":100,"ix":11},"r":{"a":0,"k":0,"ix":10},"p":{"a":0,"k":[2380.258,1747.987,0],"ix":2,"l":2},"a":{"a":0,"k":[107.913,109.787,0],"ix":1,"l":2},"s":{"a":0,"k":[100,100,100],"ix":6,"l":2}},"ao":0,"ip":84.0000034213901,"op":154.000006272549,"st":84.0000034213901,"ct":1,"bm":0}]},{"id":"comp_4","nm":"logo","fr":29.9700012207031,"layers":[{"ddd":0,"ind":1,"ty":4,"nm":"Layer 23 Outlines","sr":1,"ks":{"o":{"a":0,"k":100,"ix":11},"r":{"a":0,"k":0,"ix":10},"p":{"a":0,"k":[2521.947,2099,0],"ix":2,"l":2},"a":{"a":0,"k":[53.513,26.881,0],"ix":1,"l":2},"s":{"a":0,"k":[100,100,100],"ix":6,"l":2}},"ao":0,"shapes":[{"ty":"gr","it":[{"ind":0,"ty":"sh","ix":1,"ks":{"a":1,"k":[{"i":{"x":0.833,"y":0.833},"o":{"x":0.167,"y":0.167},"t":16,"s":[{"i":[[0,14.708],[0,0],[-14.708,0],[0,0],[0,-14.708],[14.709,0],[0,0]],"o":[[0,0],[0,-14.708],[0,0],[14.709,0],[0,14.708],[0,0],[-14.708,0]],"v":[[-0.513,-0.25],[-0.513,-0.25],[26.118,-26.881],[26.631,-26.631],[53.263,0],[26.631,26.631],[26.118,26.381]],"c":true}]},{"i":{"x":0.833,"y":0.833},"o":{"x":0.167,"y":0.167},"t":31,"s":[{"i":[[0,14.708],[0,0],[-14.708,0],[0,0],[0,-14.708],[14.709,0],[0,0]],"o":[[0,0],[0,-14.708],[0,0],[14.709,0],[0,14.708],[0,0],[-14.708,0]],"v":[[-52.263,0],[-52.263,0],[-25.632,-26.631],[26.631,-26.631],[53.263,0],[26.631,26.631],[-25.632,26.631]],"c":true}]},{"i":{"x":0.833,"y":0.833},"o":{"x":0.167,"y":0.167},"t":70,"s":[{"i":[[0,14.708],[0,0],[-14.708,0],[0,0],[0,-14.708],[14.709,0],[0,0]],"o":[[0,0],[0,-14.708],[0,0],[14.709,0],[0,14.708],[0,0],[-14.708,0]],"v":[[-52.263,0],[-52.263,0],[-25.632,-26.631],[26.631,-26.631],[53.263,0],[26.631,26.631],[-25.632,26.631]],"c":true}]},{"i":{"x":0.833,"y":0.833},"o":{"x":0.167,"y":0.167},"t":80,"s":[{"i":[[0,14.708],[0,0],[-14.708,0],[0,0],[0,-14.708],[14.709,0],[0,0]],"o":[[0,0],[0,-14.708],[0,0],[14.709,0],[0,14.708],[0,0],[-14.708,0]],"v":[[-0.513,-0.25],[-0.513,-0.25],[26.118,-26.881],[26.631,-26.631],[53.263,0],[26.631,26.631],[26.118,26.381]],"c":true}]},{"i":{"x":0.833,"y":0.833},"o":{"x":0.167,"y":0.167},"t":156,"s":[{"i":[[0,14.708],[0,0],[-14.708,0],[0,0],[0,-14.708],[14.709,0],[0,0]],"o":[[0,0],[0,-14.708],[0,0],[14.709,0],[0,14.708],[0,0],[-14.708,0]],"v":[[-0.513,-0.25],[-0.513,-0.25],[26.118,-26.881],[26.631,-26.631],[53.263,0],[26.631,26.631],[26.118,26.381]],"c":true}]},{"i":{"x":0.833,"y":0.833},"o":{"x":0.167,"y":0.167},"t":164,"s":[{"i":[[0,14.708],[0,0],[-14.708,0],[0,0],[0,-14.708],[14.709,0],[0,0]],"o":[[0,0],[0,-14.708],[0,0],[14.709,0],[0,14.708],[0,0],[-14.708,0]],"v":[[-52.263,0],[-52.263,0],[-25.632,-26.631],[26.631,-26.631],[53.263,0],[26.631,26.631],[-25.632,26.631]],"c":true}]},{"t":178.000007250089,"s":[{"i":[[0,14.708],[0,0],[-14.708,0],[0,0],[0,-14.708],[14.709,0],[0,0]],"o":[[0,0],[0,-14.708],[0,0],[14.709,0],[0,14.708],[0,0],[-14.708,0]],"v":[[-0.513,-0.25],[-0.513,-0.25],[26.118,-26.881],[26.631,-26.631],[53.263,0],[26.631,26.631],[26.118,26.381]],"c":true}]}],"ix":2},"nm":"Path 1","mn":"ADBE Vector Shape - Group","hd":false},{"ty":"fl","c":{"a":0,"k":[0.345098039216,0.949019667682,0.866666726505,1],"ix":4},"o":{"a":0,"k":100,"ix":5},"r":1,"bm":0,"nm":"Fill 1","mn":"ADBE Vector Graphic - Fill","hd":false},{"ty":"tr","p":{"a":1,"k":[{"i":{"x":0.833,"y":0.833},"o":{"x":0.167,"y":0.167},"t":0,"s":[135.513,26.881],"to":[1,0],"ti":[0.833,0]},{"i":{"x":0.833,"y":0.833},"o":{"x":0.167,"y":0.167},"t":8,"s":[141.513,26.881],"to":[-0.833,0],"ti":[13.167,0]},{"i":{"x":0.833,"y":0.833},"o":{"x":0.167,"y":0.167},"t":16,"s":[130.513,26.881],"to":[-13.167,0],"ti":[11.333,0]},{"i":{"x":0.833,"y":0.833},"o":{"x":0.167,"y":0.167},"t":31,"s":[62.513,26.881],"to":[0,0],"ti":[0,0]},{"i":{"x":0.833,"y":0.833},"o":{"x":0.167,"y":0.167},"t":70,"s":[62.513,26.881],"to":[-27.167,0],"ti":[27.167,0]},{"i":{"x":0.833,"y":0.833},"o":{"x":0.167,"y":0.167},"t":80,"s":[-100.487,26.881],"to":[0,0],"ti":[0,0]},{"i":{"x":0.833,"y":0.833},"o":{"x":0.167,"y":0.167},"t":156,"s":[-100.487,26.881],"to":[27.167,0],"ti":[-38.5,0]},{"i":{"x":0.833,"y":0.833},"o":{"x":0.167,"y":0.167},"t":164,"s":[62.513,26.881],"to":[38.5,0],"ti":[-13.167,0]},{"i":{"x":0.833,"y":0.833},"o":{"x":0.167,"y":0.167},"t":178,"s":[130.513,26.881],"to":[13.167,0],"ti":[-0.833,0]},{"i":{"x":0.833,"y":0.833},"o":{"x":0.167,"y":0.167},"t":190,"s":[141.513,26.881],"to":[0.833,0],"ti":[1,0]},{"t":201.000008186898,"s":[135.513,26.881]}],"ix":2},"a":{"a":0,"k":[0,0],"ix":1},"s":{"a":1,"k":[{"i":{"x":[0.833,0.833],"y":[0.833,0.833]},"o":{"x":[0.167,0.167],"y":[0.167,0.167]},"t":0,"s":[100,100]},{"i":{"x":[0.833,0.833],"y":[0.833,0.833]},"o":{"x":[0.167,0.167],"y":[0.167,0.167]},"t":8,"s":[75,75]},{"i":{"x":[0.833,0.833],"y":[0.833,0.833]},"o":{"x":[0.167,0.167],"y":[0.167,0.167]},"t":16,"s":[100,100]},{"i":{"x":[0.833,0.833],"y":[0.833,0.833]},"o":{"x":[0.167,0.167],"y":[0.167,0.167]},"t":70,"s":[100,100]},{"i":{"x":[0.833,0.833],"y":[0.833,0.833]},"o":{"x":[0.167,0.167],"y":[0.167,0.167]},"t":80,"s":[200,200]},{"i":{"x":[0.833,0.833],"y":[0.833,0.833]},"o":{"x":[0.167,0.167],"y":[0.167,0.167]},"t":84,"s":[0,0]},{"i":{"x":[0.833,0.833],"y":[0.833,0.833]},"o":{"x":[0.167,0.167],"y":[0.167,0.167]},"t":150,"s":[0,0]},{"i":{"x":[0.833,0.833],"y":[0.833,0.833]},"o":{"x":[0.167,0.167],"y":[0.167,0.167]},"t":156,"s":[200,200]},{"i":{"x":[0.833,0.833],"y":[0.833,0.833]},"o":{"x":[0.167,0.167],"y":[0.167,0.167]},"t":164,"s":[100,100]},{"i":{"x":[0.833,0.833],"y":[0.833,0.833]},"o":{"x":[0.167,0.167],"y":[0.167,0.167]},"t":178,"s":[100,100]},{"i":{"x":[0.833,0.833],"y":[0.833,0.833]},"o":{"x":[0.167,0.167],"y":[0.167,0.167]},"t":190,"s":[75,75]},{"t":201.000008186898,"s":[100,100]}],"ix":3},"r":{"a":0,"k":0,"ix":6},"o":{"a":0,"k":100,"ix":7},"sk":{"a":0,"k":0,"ix":4},"sa":{"a":0,"k":0,"ix":5},"nm":"Transform"}],"nm":"Group 1","np":2,"cix":2,"bm":0,"ix":1,"mn":"ADBE Vector Group","hd":false}],"ip":0,"op":226.000009205169,"st":0,"ct":1,"bm":0},{"ddd":0,"ind":3,"ty":4,"nm":"Layer 22 Outlines","sr":1,"ks":{"o":{"a":0,"k":100,"ix":11},"r":{"a":0,"k":0,"ix":10},"p":{"a":0,"k":[2625.909,2005.646,0],"ix":2,"l":2},"a":{"a":0,"k":[26.881,53.513,0],"ix":1,"l":2},"s":{"a":0,"k":[100,100,100],"ix":6,"l":2}},"ao":0,"shapes":[{"ty":"gr","it":[{"ind":0,"ty":"sh","ix":1,"ks":{"a":1,"k":[{"i":{"x":0.833,"y":0.833},"o":{"x":0.167,"y":0.167},"t":0,"s":[{"i":[[14.708,0],[0,0],[0,14.709],[0,0],[-14.708,0],[0,-14.709],[0,0]],"o":[[0,0],[-14.708,0],[0,0],[0,-14.709],[14.708,0],[0,0],[0,14.709]],"v":[[0,53.263],[0,53.263],[-26.631,26.631],[-26.603,25.369],[0.028,-1.263],[26.659,25.369],[26.631,26.631]],"c":true}]},{"i":{"x":0.833,"y":0.833},"o":{"x":0.167,"y":0.167},"t":16,"s":[{"i":[[14.708,0],[0,0],[0,14.709],[0,0],[-14.708,0],[0,-14.709],[0,0]],"o":[[0,0],[-14.708,0],[0,0],[0,-14.709],[14.708,0],[0,0],[0,14.709]],"v":[[0,53.263],[0,53.263],[-26.631,26.631],[-26.603,25.369],[0.028,-1.263],[26.659,25.369],[26.631,26.631]],"c":true}]},{"i":{"x":0.833,"y":0.833},"o":{"x":0.167,"y":0.167},"t":31,"s":[{"i":[[14.708,0],[0,0],[0,14.709],[0,0],[-14.708,0],[0,-14.709],[0,0]],"o":[[0,0],[-14.708,0],[0,0],[0,-14.709],[14.708,0],[0,0],[0,14.709]],"v":[[0,53.263],[0,53.263],[-26.631,26.631],[-26.546,-33.631],[0.085,-60.263],[26.716,-33.631],[26.631,26.631]],"c":true}]},{"i":{"x":0.833,"y":0.833},"o":{"x":0.167,"y":0.167},"t":70,"s":[{"i":[[14.708,0],[0,0],[0,14.709],[0,0],[-14.708,0],[0,-14.709],[0,0]],"o":[[0,0],[-14.708,0],[0,0],[0,-14.709],[14.708,0],[0,0],[0,14.709]],"v":[[0,53.263],[0,53.263],[-26.631,26.631],[-26.546,-33.631],[0.085,-60.263],[26.716,-33.631],[26.631,26.631]],"c":true}]},{"i":{"x":0.833,"y":0.833},"o":{"x":0.167,"y":0.167},"t":80,"s":[{"i":[[14.708,0],[0,0],[0,14.709],[0,0],[-14.708,0],[0,-14.709],[0,0]],"o":[[0,0],[-14.708,0],[0,0],[0,-14.709],[14.708,0],[0,0],[0,14.709]],"v":[[0,53.263],[0,53.263],[-26.631,26.631],[-26.603,25.369],[0.028,-1.263],[26.659,25.369],[26.631,26.631]],"c":true}]},{"i":{"x":0.833,"y":0.833},"o":{"x":0.167,"y":0.167},"t":156,"s":[{"i":[[14.708,0],[0,0],[0,14.709],[0,0],[-14.708,0],[0,-14.709],[0,0]],"o":[[0,0],[-14.708,0],[0,0],[0,-14.709],[14.708,0],[0,0],[0,14.709]],"v":[[0,53.263],[0,53.263],[-26.631,26.631],[-26.603,25.369],[0.028,-1.263],[26.659,25.369],[26.631,26.631]],"c":true}]},{"i":{"x":0.833,"y":0.833},"o":{"x":0.167,"y":0.167},"t":164,"s":[{"i":[[14.708,0],[0,0],[0,14.709],[0,0],[-14.708,0],[0,-14.709],[0,0]],"o":[[0,0],[-14.708,0],[0,0],[0,-14.709],[14.708,0],[0,0],[0,14.709]],"v":[[0,53.263],[0,53.263],[-26.631,26.631],[-26.546,-33.631],[0.085,-60.263],[26.716,-33.631],[26.631,26.631]],"c":true}]},{"i":{"x":0.833,"y":0.833},"o":{"x":0.167,"y":0.167},"t":186,"s":[{"i":[[14.708,0],[0,0],[0,14.709],[0,0],[-14.708,0],[0,-14.709],[0,0]],"o":[[0,0],[-14.708,0],[0,0],[0,-14.709],[14.708,0],[0,0],[0,14.709]],"v":[[0,53.263],[0,53.263],[-26.631,26.631],[-26.546,-33.631],[0.085,-60.263],[26.716,-33.631],[26.631,26.631]],"c":true}]},{"i":{"x":0.833,"y":0.833},"o":{"x":0.167,"y":0.167},"t":200,"s":[{"i":[[14.708,0],[0,0],[0,14.709],[0,0],[-14.708,0],[0,-14.709],[0,0]],"o":[[0,0],[-14.708,0],[0,0],[0,-14.709],[14.708,0],[0,0],[0,14.709]],"v":[[0,53.263],[0,53.263],[-26.631,26.631],[-26.603,25.369],[0.028,-1.263],[26.659,25.369],[26.631,26.631]],"c":true}]},{"t":223.000009082976,"s":[{"i":[[14.708,0],[0,0],[0,14.709],[0,0],[-14.708,0],[0,-14.709],[0,0]],"o":[[0,0],[-14.708,0],[0,0],[0,-14.709],[14.708,0],[0,0],[0,14.709]],"v":[[0,53.263],[0,53.263],[-26.631,26.631],[-26.603,25.369],[0.028,-1.263],[26.659,25.369],[26.631,26.631]],"c":true}]}],"ix":2},"nm":"Path 1","mn":"ADBE Vector Shape - Group","hd":false},{"ty":"fl","c":{"a":0,"k":[0.647058823529,0.419607873056,0.984313785329,1],"ix":4},"o":{"a":0,"k":100,"ix":5},"r":1,"bm":0,"nm":"Fill 1","mn":"ADBE Vector Graphic - Fill","hd":false},{"ty":"tr","p":{"a":1,"k":[{"i":{"x":0.833,"y":0.833},"o":{"x":0.167,"y":0.167},"t":0,"s":[31.881,121.513],"to":[0,1],"ti":[1,0]},{"i":{"x":0.833,"y":0.833},"o":{"x":0.167,"y":0.167},"t":8,"s":[31.881,127.513],"to":[-1,0],"ti":[1,11.5]},{"i":{"x":0.833,"y":0.833},"o":{"x":0.167,"y":0.167},"t":16,"s":[25.881,121.513],"to":[-1,-11.5],"ti":[0,10.5]},{"i":{"x":0.833,"y":0.833},"o":{"x":0.167,"y":0.167},"t":31,"s":[25.881,58.513],"to":[0,0],"ti":[0,0]},{"i":{"x":0.833,"y":0.833},"o":{"x":0.167,"y":0.167},"t":70,"s":[25.881,58.513],"to":[0,-26.419],"ti":[0,26.419]},{"i":{"x":0.833,"y":0.833},"o":{"x":0.167,"y":0.167},"t":80,"s":[25.881,-100],"to":[0,0],"ti":[0,0]},{"i":{"x":0.833,"y":0.833},"o":{"x":0.167,"y":0.167},"t":156,"s":[25.881,-100],"to":[0,26.419],"ti":[0,-36.919]},{"i":{"x":0.833,"y":0.833},"o":{"x":0.167,"y":0.167},"t":164,"s":[25.881,58.513],"to":[0,36.919],"ti":[-1,-11.5]},{"i":{"x":0.833,"y":0.833},"o":{"x":0.167,"y":0.167},"t":178,"s":[25.881,121.513],"to":[1,11.5],"ti":[-1,0]},{"i":{"x":0.833,"y":0.833},"o":{"x":0.167,"y":0.167},"t":190,"s":[31.881,127.513],"to":[1,0],"ti":[0,1]},{"t":201.000008186898,"s":[31.881,121.513]}],"ix":2},"a":{"a":0,"k":[0,0],"ix":1},"s":{"a":1,"k":[{"i":{"x":[0.833,0.833],"y":[0.833,0.833]},"o":{"x":[0.167,0.167],"y":[0.167,0.167]},"t":0,"s":[100,100]},{"i":{"x":[0.833,0.833],"y":[0.833,0.833]},"o":{"x":[0.167,0.167],"y":[0.167,0.167]},"t":8,"s":[75,75]},{"i":{"x":[0.833,0.833],"y":[0.833,0.833]},"o":{"x":[0.167,0.167],"y":[0.167,0.167]},"t":16,"s":[100,100]},{"i":{"x":[0.833,0.833],"y":[0.833,0.833]},"o":{"x":[0.167,0.167],"y":[0.167,0.167]},"t":70,"s":[100,100]},{"i":{"x":[0.833,0.833],"y":[0.833,0.833]},"o":{"x":[0.167,0.167],"y":[0.167,0.167]},"t":80,"s":[200,200]},{"i":{"x":[0.833,0.833],"y":[0.833,0.833]},"o":{"x":[0.167,0.167],"y":[0.167,0.167]},"t":84,"s":[0,0]},{"i":{"x":[0.833,0.833],"y":[0.833,0.833]},"o":{"x":[0.167,0.167],"y":[0.167,0.167]},"t":150,"s":[0,0]},{"i":{"x":[0.833,0.833],"y":[0.833,0.833]},"o":{"x":[0.167,0.167],"y":[0.167,0.167]},"t":156,"s":[200,200]},{"i":{"x":[0.833,0.833],"y":[0.833,0.833]},"o":{"x":[0.167,0.167],"y":[0.167,0.167]},"t":164,"s":[100,100]},{"i":{"x":[0.833,0.833],"y":[0.833,0.833]},"o":{"x":[0.167,0.167],"y":[0.167,0.167]},"t":178,"s":[100,100]},{"i":{"x":[0.833,0.833],"y":[0.833,0.833]},"o":{"x":[0.167,0.167],"y":[0.167,0.167]},"t":190,"s":[75,75]},{"t":201.000008186898,"s":[100,100]}],"ix":3},"r":{"a":0,"k":0,"ix":6},"o":{"a":0,"k":100,"ix":7},"sk":{"a":0,"k":0,"ix":4},"sa":{"a":0,"k":0,"ix":5},"nm":"Transform"}],"nm":"Group 1","np":2,"cix":2,"bm":0,"ix":1,"mn":"ADBE Vector Group","hd":false}],"ip":0,"op":226.000009205169,"st":0,"ct":1,"bm":0},{"ddd":0,"ind":5,"ty":4,"nm":"Layer 21 Outlines","sr":1,"ks":{"o":{"a":0,"k":100,"ix":11},"r":{"a":0,"k":0,"ix":10},"p":{"a":0,"k":[2719.043,2099,0],"ix":2,"l":2},"a":{"a":0,"k":[53.513,26.881,0],"ix":1,"l":2},"s":{"a":0,"k":[100,100,100],"ix":6,"l":2}},"ao":0,"shapes":[{"ty":"gr","it":[{"ind":0,"ty":"sh","ix":1,"ks":{"a":1,"k":[{"i":{"x":0.833,"y":0.833},"o":{"x":0.167,"y":0.167},"t":16,"s":[{"i":[[0,-14.708],[0,0],[14.708,0],[0,0],[0,14.708],[-14.708,0],[0,0]],"o":[[0,0],[0,14.708],[0,0],[-14.708,0],[0,-14.708],[0,0],[14.708,0]],"v":[[0.263,0],[0.263,0],[-25.368,26.631],[-26.631,26.631],[-53.263,0],[-26.631,-26.631],[-25.368,-26.631]],"c":true}]},{"i":{"x":0.833,"y":0.833},"o":{"x":0.167,"y":0.167},"t":31,"s":[{"i":[[0,-14.708],[0,0],[14.708,0],[0,0],[0,14.708],[-14.708,0],[0,0]],"o":[[0,0],[0,14.708],[0,0],[-14.708,0],[0,-14.708],[0,0],[14.708,0]],"v":[[53.263,0.205],[53.263,0.205],[27.632,26.836],[-26.631,26.631],[-53.263,0],[-26.631,-26.631],[27.632,-26.426]],"c":true}]},{"i":{"x":0.833,"y":0.833},"o":{"x":0.167,"y":0.167},"t":70,"s":[{"i":[[0,-14.708],[0,0],[14.708,0],[0,0],[0,14.708],[-14.708,0],[0,0]],"o":[[0,0],[0,14.708],[0,0],[-14.708,0],[0,-14.708],[0,0],[14.708,0]],"v":[[53.263,0.205],[53.263,0.205],[27.632,26.836],[-26.631,26.631],[-53.263,0],[-26.631,-26.631],[27.632,-26.426]],"c":true}]},{"i":{"x":0.833,"y":0.833},"o":{"x":0.167,"y":0.167},"t":80,"s":[{"i":[[0,-14.708],[0,0],[14.708,0],[0,0],[0,14.708],[-14.708,0],[0,0]],"o":[[0,0],[0,14.708],[0,0],[-14.708,0],[0,-14.708],[0,0],[14.708,0]],"v":[[0.263,0],[0.263,0],[-25.368,26.631],[-26.631,26.631],[-53.263,0],[-26.631,-26.631],[-25.368,-26.631]],"c":true}]},{"i":{"x":0.833,"y":0.833},"o":{"x":0.167,"y":0.167},"t":156,"s":[{"i":[[0,-14.708],[0,0],[14.708,0],[0,0],[0,14.708],[-14.708,0],[0,0]],"o":[[0,0],[0,14.708],[0,0],[-14.708,0],[0,-14.708],[0,0],[14.708,0]],"v":[[0.263,0],[0.263,0],[-25.368,26.631],[-26.631,26.631],[-53.263,0],[-26.631,-26.631],[-25.368,-26.631]],"c":true}]},{"i":{"x":0.833,"y":0.833},"o":{"x":0.167,"y":0.167},"t":164,"s":[{"i":[[0,-14.708],[0,0],[14.708,0],[0,0],[0,14.708],[-14.708,0],[0,0]],"o":[[0,0],[0,14.708],[0,0],[-14.708,0],[0,-14.708],[0,0],[14.708,0]],"v":[[53.263,0.205],[53.263,0.205],[27.632,26.836],[-26.631,26.631],[-53.263,0],[-26.631,-26.631],[27.632,-26.426]],"c":true}]},{"i":{"x":0.833,"y":0.833},"o":{"x":0.167,"y":0.167},"t":186,"s":[{"i":[[0,-14.708],[0,0],[14.708,0],[0,0],[0,14.708],[-14.708,0],[0,0]],"o":[[0,0],[0,14.708],[0,0],[-14.708,0],[0,-14.708],[0,0],[14.708,0]],"v":[[53.263,0.205],[53.263,0.205],[27.632,26.836],[-26.631,26.631],[-53.263,0],[-26.631,-26.631],[27.632,-26.426]],"c":true}]},{"t":200.000008146167,"s":[{"i":[[0,-14.708],[0,0],[14.708,0],[0,0],[0,14.708],[-14.708,0],[0,0]],"o":[[0,0],[0,14.708],[0,0],[-14.708,0],[0,-14.708],[0,0],[14.708,0]],"v":[[0.263,0],[0.263,0],[-25.368,26.631],[-26.631,26.631],[-53.263,0],[-26.631,-26.631],[-25.368,-26.631]],"c":true}]}],"ix":2},"nm":"Path 1","mn":"ADBE Vector Shape - Group","hd":false},{"ty":"fl","c":{"a":0,"k":[0.992156922583,0.87450986376,0.427451010311,1],"ix":4},"o":{"a":0,"k":100,"ix":5},"r":1,"bm":0,"nm":"Fill 1","mn":"ADBE Vector Graphic - Fill","hd":false},{"ty":"tr","p":{"a":1,"k":[{"i":{"x":0.833,"y":0.833},"o":{"x":0.167,"y":0.167},"t":0,"s":[-9.487,26.881],"to":[0,0],"ti":[0,0]},{"i":{"x":0.833,"y":0.833},"o":{"x":0.167,"y":0.167},"t":8,"s":[-15.687,26.881],"to":[0,0],"ti":[0,0]},{"i":{"x":0.833,"y":0.833},"o":{"x":0.167,"y":0.167},"t":16,"s":[-14.487,26.881],"to":[11.167,0],"ti":[-12,0]},{"i":{"x":0.833,"y":0.833},"o":{"x":0.167,"y":0.167},"t":31,"s":[57.513,26.881],"to":[0,0],"ti":[0,0]},{"i":{"x":0.833,"y":0.833},"o":{"x":0.167,"y":0.167},"t":70,"s":[57.513,26.881],"to":[29.667,0],"ti":[-29.667,0]},{"i":{"x":0.833,"y":0.833},"o":{"x":0.167,"y":0.167},"t":80,"s":[235.513,26.881],"to":[0,0],"ti":[0,0]},{"i":{"x":0.833,"y":0.833},"o":{"x":0.167,"y":0.167},"t":156,"s":[235.513,26.881],"to":[-29.667,0],"ti":[41.667,0]},{"i":{"x":0.833,"y":0.833},"o":{"x":0.167,"y":0.167},"t":164,"s":[57.513,26.881],"to":[-41.667,0],"ti":[0,0]},{"i":{"x":0.833,"y":0.833},"o":{"x":0.167,"y":0.167},"t":178,"s":[-14.487,26.881],"to":[11.167,0],"ti":[0,0]},{"i":{"x":0.833,"y":0.833},"o":{"x":0.167,"y":0.167},"t":190,"s":[-15.687,26.881],"to":[0,0],"ti":[0,0]},{"t":201.000008186898,"s":[-9.487,26.881]}],"ix":2},"a":{"a":0,"k":[0,0],"ix":1},"s":{"a":1,"k":[{"i":{"x":[0.833,0.833],"y":[0.833,0.833]},"o":{"x":[0.167,0.167],"y":[0.167,0.167]},"t":0,"s":[100,100]},{"i":{"x":[0.833,0.833],"y":[0.833,0.833]},"o":{"x":[0.167,0.167],"y":[0.167,0.167]},"t":8,"s":[75,75]},{"i":{"x":[0.833,0.833],"y":[0.833,0.833]},"o":{"x":[0.167,0.167],"y":[0.167,0.167]},"t":16,"s":[100,100]},{"i":{"x":[0.833,0.833],"y":[0.833,0.833]},"o":{"x":[0.167,0.167],"y":[0.167,0.167]},"t":70,"s":[100,100]},{"i":{"x":[0.833,0.833],"y":[0.833,0.833]},"o":{"x":[0.167,0.167],"y":[0.167,0.167]},"t":80,"s":[200,200]},{"i":{"x":[0.833,0.833],"y":[0.833,0.833]},"o":{"x":[0.167,0.167],"y":[0.167,0.167]},"t":84,"s":[0,0]},{"i":{"x":[0.833,0.833],"y":[0.833,0.833]},"o":{"x":[0.167,0.167],"y":[0.167,0.167]},"t":150,"s":[0,0]},{"i":{"x":[0.833,0.833],"y":[0.833,0.833]},"o":{"x":[0.167,0.167],"y":[0.167,0.167]},"t":156,"s":[200,200]},{"i":{"x":[0.833,0.833],"y":[0.833,0.833]},"o":{"x":[0.167,0.167],"y":[0.167,0.167]},"t":164,"s":[100,100]},{"i":{"x":[0.833,0.833],"y":[0.833,0.833]},"o":{"x":[0.167,0.167],"y":[0.167,0.167]},"t":178,"s":[100,100]},{"i":{"x":[0.833,0.833],"y":[0.833,0.833]},"o":{"x":[0.167,0.167],"y":[0.167,0.167]},"t":190,"s":[75,75]},{"t":201.000008186898,"s":[100,100]}],"ix":3},"r":{"a":0,"k":0,"ix":6},"o":{"a":0,"k":100,"ix":7},"sk":{"a":0,"k":0,"ix":4},"sa":{"a":0,"k":0,"ix":5},"nm":"Transform"}],"nm":"Group 1","np":2,"cix":2,"bm":0,"ix":1,"mn":"ADBE Vector Group","hd":false}],"ip":0,"op":226.000009205169,"st":0,"ct":1,"bm":0},{"ddd":0,"ind":7,"ty":4,"nm":"Layer 20 Outlines","sr":1,"ks":{"o":{"a":0,"k":100,"ix":11},"r":{"a":0,"k":0,"ix":10},"p":{"a":0,"k":[2625.909,2199.097,0],"ix":2,"l":2},"a":{"a":0,"k":[26.881,53.513,0],"ix":1,"l":2},"s":{"a":0,"k":[100,100,100],"ix":6,"l":2}},"ao":0,"shapes":[{"ty":"gr","it":[{"ind":0,"ty":"sh","ix":1,"ks":{"a":1,"k":[{"i":{"x":0.833,"y":0.833},"o":{"x":0.167,"y":0.167},"t":0,"s":[{"i":[[14.708,0],[0,0],[0,14.708],[0,0],[-14.708,0],[0,-14.708],[0,0]],"o":[[0,0],[-14.708,0],[0,0],[0,-14.708],[14.708,0],[0,0],[0,14.708]],"v":[[-0.222,0.763],[-0.222,0.763],[-26.853,-25.868],[-26.631,-26.631],[0,-53.263],[26.631,-26.631],[26.409,-25.868]],"c":true}]},{"i":{"x":0.833,"y":0.833},"o":{"x":0.167,"y":0.167},"t":16,"s":[{"i":[[14.708,0],[0,0],[0,14.708],[0,0],[-14.708,0],[0,-14.708],[0,0]],"o":[[0,0],[-14.708,0],[0,0],[0,-14.708],[14.708,0],[0,0],[0,14.708]],"v":[[-0.222,0.763],[-0.222,0.763],[-26.853,-25.868],[-26.631,-26.631],[0,-53.263],[26.631,-26.631],[26.409,-25.868]],"c":true}]},{"i":{"x":0.833,"y":0.833},"o":{"x":0.167,"y":0.167},"t":31,"s":[{"i":[[14.708,0],[0,0],[0,14.708],[0,0],[-14.708,0],[0,-14.708],[0,0]],"o":[[0,0],[-14.708,0],[0,0],[0,-14.708],[14.708,0],[0,0],[0,14.708]],"v":[[-0.415,62.763],[-0.415,62.763],[-27.046,36.132],[-26.631,-26.631],[0,-53.263],[26.631,-26.631],[26.216,36.132]],"c":true}]},{"i":{"x":0.833,"y":0.833},"o":{"x":0.167,"y":0.167},"t":70,"s":[{"i":[[14.708,0],[0,0],[0,14.708],[0,0],[-14.708,0],[0,-14.708],[0,0]],"o":[[0,0],[-14.708,0],[0,0],[0,-14.708],[14.708,0],[0,0],[0,14.708]],"v":[[-0.415,62.763],[-0.415,62.763],[-27.046,36.132],[-26.631,-26.631],[0,-53.263],[26.631,-26.631],[26.216,36.132]],"c":true}]},{"i":{"x":0.833,"y":0.833},"o":{"x":0.167,"y":0.167},"t":80,"s":[{"i":[[14.708,0],[0,0],[0,14.708],[0,0],[-14.708,0],[0,-14.708],[0,0]],"o":[[0,0],[-14.708,0],[0,0],[0,-14.708],[14.708,0],[0,0],[0,14.708]],"v":[[-0.222,0.763],[-0.222,0.763],[-26.853,-25.868],[-26.631,-26.631],[0,-53.263],[26.631,-26.631],[26.409,-25.868]],"c":true}]},{"i":{"x":0.833,"y":0.833},"o":{"x":0.167,"y":0.167},"t":156,"s":[{"i":[[14.708,0],[0,0],[0,14.708],[0,0],[-14.708,0],[0,-14.708],[0,0]],"o":[[0,0],[-14.708,0],[0,0],[0,-14.708],[14.708,0],[0,0],[0,14.708]],"v":[[-0.222,0.763],[-0.222,0.763],[-26.853,-25.868],[-26.631,-26.631],[0,-53.263],[26.631,-26.631],[26.409,-25.868]],"c":true}]},{"i":{"x":0.833,"y":0.833},"o":{"x":0.167,"y":0.167},"t":164,"s":[{"i":[[14.708,0],[0,0],[0,14.708],[0,0],[-14.708,0],[0,-14.708],[0,0]],"o":[[0,0],[-14.708,0],[0,0],[0,-14.708],[14.708,0],[0,0],[0,14.708]],"v":[[-0.415,62.763],[-0.415,62.763],[-27.046,36.132],[-26.631,-26.631],[0,-53.263],[26.631,-26.631],[26.216,36.132]],"c":true}]},{"i":{"x":0.833,"y":0.833},"o":{"x":0.167,"y":0.167},"t":186,"s":[{"i":[[14.708,0],[0,0],[0,14.708],[0,0],[-14.708,0],[0,-14.708],[0,0]],"o":[[0,0],[-14.708,0],[0,0],[0,-14.708],[14.708,0],[0,0],[0,14.708]],"v":[[-0.415,62.763],[-0.415,62.763],[-27.046,36.132],[-26.631,-26.631],[0,-53.263],[26.631,-26.631],[26.216,36.132]],"c":true}]},{"i":{"x":0.833,"y":0.833},"o":{"x":0.167,"y":0.167},"t":200,"s":[{"i":[[14.708,0],[0,0],[0,14.708],[0,0],[-14.708,0],[0,-14.708],[0,0]],"o":[[0,0],[-14.708,0],[0,0],[0,-14.708],[14.708,0],[0,0],[0,14.708]],"v":[[-0.222,0.763],[-0.222,0.763],[-26.853,-25.868],[-26.631,-26.631],[0,-53.263],[26.631,-26.631],[26.409,-25.868]],"c":true}]},{"t":223.000009082976,"s":[{"i":[[14.708,0],[0,0],[0,14.708],[0,0],[-14.708,0],[0,-14.708],[0,0]],"o":[[0,0],[-14.708,0],[0,0],[0,-14.708],[14.708,0],[0,0],[0,14.708]],"v":[[-0.222,0.763],[-0.222,0.763],[-26.853,-25.868],[-26.631,-26.631],[0,-53.263],[26.631,-26.631],[26.409,-25.868]],"c":true}]}],"ix":2},"nm":"Path 1","mn":"ADBE Vector Shape - Group","hd":false},{"ty":"fl","c":{"a":0,"k":[0.984313785329,0.690196078431,0.231372563979,1],"ix":4},"o":{"a":0,"k":100,"ix":5},"r":1,"bm":0,"nm":"Fill 1","mn":"ADBE Vector Graphic - Fill","hd":false},{"ty":"tr","p":{"a":1,"k":[{"i":{"x":0.833,"y":0.833},"o":{"x":0.167,"y":0.167},"t":0,"s":[30.931,-19.487],"to":[0,-1.167],"ti":[0.833,0.167]},{"i":{"x":0.833,"y":0.833},"o":{"x":0.167,"y":0.167},"t":8,"s":[30.931,-26.487],"to":[-0.833,-0.167],"ti":[0.833,-10.333]},{"i":{"x":0.833,"y":0.833},"o":{"x":0.167,"y":0.167},"t":16,"s":[25.931,-20.487],"to":[-0.833,10.333],"ti":[0,-9.333]},{"i":{"x":0.833,"y":0.833},"o":{"x":0.167,"y":0.167},"t":31,"s":[25.931,35.513],"to":[0,0],"ti":[0,0]},{"i":{"x":0.833,"y":0.833},"o":{"x":0.167,"y":0.167},"t":70,"s":[25.931,35.513],"to":[0,27.5],"ti":[0,-27.5]},{"i":{"x":0.833,"y":0.833},"o":{"x":0.167,"y":0.167},"t":80,"s":[25.931,200.513],"to":[0,0],"ti":[0,0]},{"i":{"x":0.833,"y":0.833},"o":{"x":0.167,"y":0.167},"t":156,"s":[25.931,200.513],"to":[0,-27.5],"ti":[0,36.833]},{"i":{"x":0.833,"y":0.833},"o":{"x":0.167,"y":0.167},"t":164,"s":[25.931,35.513],"to":[0,-36.833],"ti":[-0.833,10.333]},{"i":{"x":0.833,"y":0.833},"o":{"x":0.167,"y":0.167},"t":178,"s":[25.931,-20.487],"to":[0.833,-10.333],"ti":[-0.833,-0.167]},{"i":{"x":0.833,"y":0.833},"o":{"x":0.167,"y":0.167},"t":190,"s":[30.931,-26.487],"to":[0.833,0.167],"ti":[0,-1.167]},{"t":201.000008186898,"s":[30.931,-19.487]}],"ix":2},"a":{"a":0,"k":[0,0],"ix":1},"s":{"a":1,"k":[{"i":{"x":[0.833,0.833],"y":[0.833,0.833]},"o":{"x":[0.167,0.167],"y":[0.167,0.167]},"t":0,"s":[100,100]},{"i":{"x":[0.833,0.833],"y":[0.833,0.833]},"o":{"x":[0.167,0.167],"y":[0.167,0.167]},"t":8,"s":[75,75]},{"i":{"x":[0.833,0.833],"y":[0.833,0.833]},"o":{"x":[0.167,0.167],"y":[0.167,0.167]},"t":16,"s":[100,100]},{"i":{"x":[0.833,0.833],"y":[0.833,0.833]},"o":{"x":[0.167,0.167],"y":[0.167,0.167]},"t":70,"s":[100,100]},{"i":{"x":[0.833,0.833],"y":[0.833,0.833]},"o":{"x":[0.167,0.167],"y":[0.167,0.167]},"t":80,"s":[200,200]},{"i":{"x":[0.833,0.833],"y":[0.833,0.833]},"o":{"x":[0.167,0.167],"y":[0.167,0.167]},"t":84,"s":[0,0]},{"i":{"x":[0.833,0.833],"y":[0.833,0.833]},"o":{"x":[0.167,0.167],"y":[0.167,0.167]},"t":150,"s":[0,0]},{"i":{"x":[0.833,0.833],"y":[0.833,0.833]},"o":{"x":[0.167,0.167],"y":[0.167,0.167]},"t":156,"s":[200,200]},{"i":{"x":[0.833,0.833],"y":[0.833,0.833]},"o":{"x":[0.167,0.167],"y":[0.167,0.167]},"t":164,"s":[100,100]},{"i":{"x":[0.833,0.833],"y":[0.833,0.833]},"o":{"x":[0.167,0.167],"y":[0.167,0.167]},"t":178,"s":[100,100]},{"i":{"x":[0.833,0.833],"y":[0.833,0.833]},"o":{"x":[0.167,0.167],"y":[0.167,0.167]},"t":190,"s":[75,75]},{"t":201.000008186898,"s":[100,100]}],"ix":3},"r":{"a":0,"k":0,"ix":6},"o":{"a":0,"k":100,"ix":7},"sk":{"a":0,"k":0,"ix":4},"sa":{"a":0,"k":0,"ix":5},"nm":"Transform"}],"nm":"Group 1","np":2,"cix":2,"bm":0,"ix":1,"mn":"ADBE Vector Group","hd":false}],"ip":0,"op":226.000009205169,"st":0,"ct":1,"bm":0}]}],"layers":[{"ddd":0,"ind":1,"ty":0,"nm":"chair","refId":"comp_0","sr":1,"ks":{"o":{"a":0,"k":100,"ix":11},"r":{"a":0,"k":0,"ix":10},"p":{"a":0,"k":[2622.5,2098,0],"ix":2,"l":2},"a":{"a":0,"k":[2622.5,2098,0],"ix":1,"l":2},"s":{"a":0,"k":[100,100,100],"ix":6,"l":2}},"ao":0,"w":5245,"h":4196,"ip":0,"op":226.000009205169,"st":0,"bm":0},{"ddd":0,"ind":3,"ty":0,"nm":"flower","refId":"comp_1","sr":1,"ks":{"o":{"a":0,"k":100,"ix":11},"r":{"a":0,"k":0,"ix":10},"p":{"a":0,"k":[2622.5,2098,0],"ix":2,"l":2},"a":{"a":0,"k":[2622.5,2098,0],"ix":1,"l":2},"s":{"a":0,"k":[100,100,100],"ix":6,"l":2}},"ao":0,"w":5245,"h":4196,"ip":0,"op":226.000009205169,"st":0,"bm":0},{"ddd":0,"ind":7,"ty":0,"nm":"Ac","refId":"comp_2","sr":1,"ks":{"o":{"a":0,"k":100,"ix":11},"r":{"a":0,"k":0,"ix":10},"p":{"a":0,"k":[2622.5,2098,0],"ix":2,"l":2},"a":{"a":0,"k":[2622.5,2098,0],"ix":1,"l":2},"s":{"a":0,"k":[100,100,100],"ix":6,"l":2}},"ao":0,"w":5245,"h":4196,"ip":0,"op":226.000009205169,"st":0,"bm":0},{"ddd":0,"ind":8,"ty":0,"nm":"light","refId":"comp_3","sr":1,"ks":{"o":{"a":0,"k":100,"ix":11},"r":{"a":0,"k":0,"ix":10},"p":{"a":0,"k":[2622.5,2098,0],"ix":2,"l":2},"a":{"a":0,"k":[2622.5,2098,0],"ix":1,"l":2},"s":{"a":0,"k":[100,100,100],"ix":6,"l":2}},"ao":0,"w":5245,"h":4196,"ip":0,"op":226.000009205169,"st":0,"bm":0},{"ddd":0,"ind":10,"ty":0,"nm":"logo","refId":"comp_4","sr":1,"ks":{"o":{"a":0,"k":100,"ix":11},"r":{"a":1,"k":[{"i":{"x":[0.833],"y":[0.833]},"o":{"x":[0.167],"y":[0.167]},"t":31,"s":[0]},{"t":61.0000024845809,"s":[318]}],"ix":10},"p":{"a":0,"k":[2622.5,2034,0],"ix":2,"l":2},"a":{"a":0,"k":[2622.5,2098,0],"ix":1,"l":2},"s":{"a":0,"k":[100,100,100],"ix":6,"l":2}},"ao":0,"w":5245,"h":4196,"ip":0,"op":226.000009205169,"st":0,"bm":0},{"ddd":0,"ind":11,"ty":2,"nm":"Layer 1","refId":"image_13","sr":1,"ks":{"o":{"a":0,"k":100,"ix":11},"r":{"a":0,"k":0,"ix":10},"p":{"a":0,"k":[2622.385,2097.912,0],"ix":2,"l":2},"a":{"a":0,"k":[2622.635,2098.158,0],"ix":1,"l":2},"s":{"a":0,"k":[100,100,100],"ix":6,"l":2}},"ao":0,"ip":0,"op":226.000009205169,"st":0,"bm":0}],"markers":[],"props":{}}